cqh_push/__init__.py
cqh_push/run.py
cqh_push-0.0.5.dist-info/METADATA
cqh_push-0.0.5.dist-info/WHEEL
cqh_push-0.0.5.dist-info/entry_points.txt
cqh_push-0.0.5.dist-info/top_level.txt
cqh_push-0.0.5.dist-info/RECORD
