Metadata-Version: 2.1
Name: cqh-push
Version: 0.0.5
Summary: get current branch and git push origin ${bransh} 
Home-page: https://github.com/chen19901225/cqh_tail
Author: chenqinghe
Author-email: 1832866299@qq.com
License: UNKNOWN
Platform: UNKNOWN
Classifier: Programming Language :: Python :: 3
Classifier: License :: OSI Approved :: MIT License
Classifier: Operating System :: Unix
Requires-Python: >=3.6
Requires-Dist: gitpython
